mbu_msoffice_integration/__init__.py
mbu_msoffice_integration/excel_reader.py
mbu_msoffice_integration/sharepoint_class.py
mbu_msoffice_integration-1.0.6.dist-info/licenses/LICENSE
mbu_msoffice_integration-1.0.6.dist-info/METADATA
mbu_msoffice_integration-1.0.6.dist-info/WHEEL
mbu_msoffice_integration-1.0.6.dist-info/top_level.txt
mbu_msoffice_integration-1.0.6.dist-info/RECORD
