Metadata-Version: 2.4
Name: mbu_msoffice_integration
Version: 1.0.6
Summary: Repo containing functionality related to MSOffice
Author-email: MBU <rpa@mbu.aarhus.dk>
License-Expression: MIT
Classifier: Programming Language :: Python :: 3
Classifier: Operating System :: Microsoft :: Windows
Requires-Python: >=3.7
License-File: LICENSE
Requires-Dist: cryptography>=43.0.0
Requires-Dist: pyodbc>=5.1.0
Requires-Dist: python-dateutil==2.9.*
Requires-Dist: openpyxl>=3.1.2
Requires-Dist: pandas>=2.2.3
Requires-Dist: office365-rest-python-client
Dynamic: license-file
